{"AU":{"226":"M, Suriya","240":"Yan, Fei; Li, Nianqiao; Iliyasu, Abdullah M.; Salama, Ahmed S.; Hirota, Kaoru","987":"Bhugaonkar, Kunal; Bhugaonkar, Roshan; Masne, Neha","1196":"Peral-Garcia, David; Cruz-Benito, Juan; Garcia-Penalvo, Francisco Jose","1222":"Williams, Phillip; Dutta, Indira Kaylan; Daoud, Hisham; Bayoumi, Magdy","2090":"Cherbal, Sarra; Zier, Abdelhak; Hebal, Sara; Louail, Lemia; Annane, Boubakeur","2091":"Prateek, Kumar; Ojha, Nitish Kumar; Altaf, Fahiem; Maity, Soumyadev","2160":"Zhao, Ning; Zhang, Haoran; Yang, Xiaohu; Yan, Jinyue; You, Fengqi","2185":"Akbar, Sana; Saritha, Sri Khetwat","2620":"Sarwar, Muhammad Imran; Maghrabi, Louai A.; Khan, Imran; Naith, Qamar H.; Nisar, Kashif","2768":"Satish Babu, Battula V.; Babu, Kare Suresh","3037":"Paudel, Hari P.; Crawford, Scott E.; Lee, Yueh-Lin; Shugayev, Roman A.; Leuenberger, Michael N.; Syamlal, Madhava; Ohodnicki, Paul R.; Lu, Ping; Mollot, Darren; Duan, Yuhua","3066":"Kumar, Gulshan; Altalbe, Ali","3106":"Jeswal, S. K.; Chakraverty, S.","3252":"Ahmad, Tanveer; Zhang, Dongdong","3258":"Gill, Sukhpal Singh; Wu, Huaming; Patros, Panos; Ottaviani, Carlo; Arora, Priyansh; Pujol, Victor Casamayor; Haunschild, David; Parlikad, Ajith Kumar; Cetinkaya, Oktay; Lutfiyya, Hanan; Stankovski, Vlado; Li, Ruidong; Ding, Yuemin; Qadir, Junaid; Abraham, Ajith; Ghosh, Soumya K.; Song, Houbing Herbert; Sakellariou, Rizos; Rana, Omer; Rodrigues, Joel J.P.C.; Kanhere, Salil S.; Dustdar, Schahram; Uhlig, Steve; Ramamohanarao, Kotagiri; Buyya, Rajkumar","3396":"Rozenman, Georgi Gary; Kundu, Neel Kanth; Liu, Ruiqi; Zhang, Leyi; Maslennikov, Alona; Reches, Yuval; Youm, Heung Youl","3734":"Kishor, Kaushal","3782":"Mahmoudi, Yousra; Zioui, Nadjet; Belbachir, Hac\u00e8ne; Tadjine, Mohamed; Rezgui, Abdelmounaam","3834":"Balogh, Stefan; Gallo, Ondrej; Ploszek, Roderik; Spacek, Peter; Zajac, Pavol","3857":"Phillipson, Frank"},"PY":{"226":2022,"240":2023,"987":2022,"1196":2024,"1222":2022,"2090":2024,"2091":2023,"2160":2023,"2185":2020,"2620":2023,"2768":2021,"3037":2023,"3066":2024,"3106":2019,"3252":2021,"3258":2024,"3396":2023,"3734":2023,"3782":2023,"3834":2021,"3857":2023},"DI":{"226":"10.1016\/J.IJIN.2022.11.004","240":"10.1016\/J.JISA.2023.103621","987":"10.7759\/CUREUS.29071","1196":"10.1016\/J.COSREV.2024.100619","1222":"10.1016\/J.IOT.2022.100564","2090":"10.1007\/S11227-023-05616-2","2091":"10.1007\/S11235-022-00979-Y","2160":"10.1016\/J.ADAPEN.2023.100125","2185":"10.1016\/J.COSREV.2020.100313","2620":"10.1109\/ACCESS.2023.3342079","2768":"10.18280\/ISI.260104","3037":"10.1002\/QUTE.202300096","3066":"10.1007\/S10668-024-04790-4","3106":"10.1007\/S11831-018-9269-0","3252":"10.1016\/J.SCS.2021.102783","3258":"10.1016\/J.TELER.2024.100116","3396":"10.1049\/QTC2.12069","3734":"10.1515\/9783110798159-012","3782":"10.28991\/ESJ-2023-07-01-020","3834":"10.3390\/ELECTRONICS10212647","3857":"10.3390\/MATH11153423"}}